miksisdk-0.0.8.dist-info/WHEEL
miksisdk-0.0.8.dist-info/top_level.txt
miksisdk-0.0.8.dist-info/RECORD
miksisdk-0.0.8.dist-info/METADATA
miksisdk/graphtool.cpython-310-i386-linux-gnu.so
miksisdk/api.cpython-310-i386-linux-gnu.so
miksisdk/forecast_tool.cpython-310-i386-linux-gnu.so
miksisdk/base.cpython-310-i386-linux-gnu.so
miksisdk/agent.cpython-310-i386-linux-gnu.so
miksisdk/__init__.cpython-310-i386-linux-gnu.so
